Shape4D/Constant.py
Shape4D/Shapes.py
Shape4D/Utils.py
Shape4D/VisualShapes.py
Shape4D/__init__.py
Shape4D-0.2.8.dist-info/LICENSE
Shape4D-0.2.8.dist-info/METADATA
Shape4D-0.2.8.dist-info/WHEEL
Shape4D-0.2.8.dist-info/top_level.txt
Shape4D-0.2.8.dist-info/RECORD
