Metadata-Version: 2.1
Name: Shape4D
Version: 0.2.8
Summary: A small library for visible 3D shapes
Home-page: UNKNOWN
Author: Liqun He, WanZheng He, Jun Hu
Author-email: heliqun@ustc.edu.cn
License: UNKNOWN
Platform: UNKNOWN
Classifier: Programming Language :: Python :: 3
Classifier: License :: OSI Approved :: MIT License
Classifier: Operating System :: OS Independent
Requires-Python: >=3.6
License-File: LICENSE
